check/__init__.py
check/helpers.py
zbd_tools-1.0.1.dist-info/METADATA
zbd_tools-1.0.1.dist-info/WHEEL
zbd_tools-1.0.1.dist-info/entry_points.txt
zbd_tools-1.0.1.dist-info/top_level.txt
zbd_tools-1.0.1.dist-info/RECORD
