Metadata-Version: 2.1
Name: zbd_tools
Version: 1.0.1
Summary: A set of tools used to determine Zoned Storage Support
Author-email: Tommy McGee <tommy.mcgee@opensource.wdc.com>
Project-URL: homepage, https://zonedstorage.io/
Keywords: zoned,storage,zoned storage
Classifier: Programming Language :: Python :: 3
Classifier: License :: OSI Approved :: GNU General Public License v3 (GPLv3)
Classifier: Operating System :: OS Independent
Requires-Python: >=3.0
